miniproject03++/memory_quarter.sv
`timescale 10ns/10ns

module memory_quarter #(
    parameter INIT_FILE = ""
)(
    input  logic       clk,
    input  logic [6:0] read_address, // 7-bit address (0 to 127)
    output logic [8:0] read_data     // 9-bit sample
);

    // Declare memory array for storing 128 9-bit samples of the first quarter cycle
    logic [8:0] sample_memory [0:127];

    // Load samples from INIT_FILE if provided
    initial if (INIT_FILE != "") begin
        $readmemh(INIT_FILE, sample_memory);
    end

    // Synchronous read from the memory array
    always_ff @(posedge clk) begin
        read_data <= sample_memory[read_address];
    end

endmodule

miniproject03++/sine_gen.sv
`timescale 10ns/10ns

module sine_gen(
    input  logic        clk,
    input  logic [8:0]   phase,    // 9-bit input: 0-511
    output logic [9:0]   out       // 10-bit output: centered around 512
);

    // Split phase into quadrant and index
    logic [1:0] quadrant;
    logic [6:0] quarter_address;
    logic [8:0] quarter_data;

    assign quadrant        = phase[8:7];
    assign quarter_address = (quadrant == 2'b01 || quadrant == 2'b11) ? (7'd127 - phase[6:0])
                                                                     : phase[6:0];

    // Quarter-cycle memory lookup
    memory_quarter #(
        .INIT_FILE("sine_quarter.txt")
    ) mem_inst (
        .clk(clk),
        .read_address(quarter_address),
        .read_data(quarter_data)
    );

    // Generate full-cycle sine from quarter lookup
    always_comb begin
        case (quadrant)
            2'b00, 2'b01: out = 10'd512 + quarter_data; // positive half
            2'b10, 2'b11: out = 10'd512 - quarter_data; // negative half
            default:      out = 10'd512;
        endcase
    end

endmodule

miniproject03++/top.sv
`timescale 10ns/10ns

module top(
    input  logic       clk,         // 12 MHz board oscillator
    input  logic       boot_n,      // BOOT button (active low)
    input  logic       sw_n,        //  SW  button (active low)
    output logic [9:0] dac_out      // 10-bit to R-2R ladder
);

  //-------------------------------------------------------------------------
  // 1) Button Synchronizers & Edge Detectors
  //-------------------------------------------------------------------------
  logic boot_sync0, boot_sync1, boot_r;
  logic sw_sync0,   sw_sync1,   sw_r;

  // two-stage sync + invert active-low
  always_ff @(posedge clk) begin
    boot_sync0 <= ~boot_n;
    boot_sync1 <= boot_sync0;
    sw_sync0   <= ~sw_n;
    sw_sync1   <= sw_sync0;
  end

  // detect rising edge (single pulse per press)
  always_ff @(posedge clk) begin
    boot_r <= boot_sync1 & ~boot_r;
    sw_r   <= sw_sync1   & ~sw_r;
  end

  //-------------------------------------------------------------------------
  // 2) Control Registers
  //-------------------------------------------------------------------------
  // waveform: 00=sine, 01=triangle, 10=square
  logic [1:0] waveform_sel = 2'b00;  
  // freq index: 0→1 kHz, 1→2 kHz, 2→5 kHz, 3→10 kHz
  logic [1:0] freq_sel     = 2'b00;  

  always_ff @(posedge clk) begin
    if (boot_r) waveform_sel <= (waveform_sel == 2'd2) ? 2'd0 : waveform_sel + 1;
    if ( sw_r)   freq_sel     <= (freq_sel     == 2'd3) ? 2'd0 : freq_sel     + 1;
  end

  //-------------------------------------------------------------------------
  // 3) Phase–Increment Lookup
  //-------------------------------------------------------------------------
  // sample clock = 12 MHz
  localparam PH1 = 32'd357_913;   // ~1 kHz: 1e3*2^32/12e6
  localparam PH2 = 32'd715_827;   // ~2 kHz
  localparam PH5 = 32'd1_789_574; // ~5 kHz
  localparam PH10= 32'd3_578_139; // ~10 kHz

  logic [31:0] phase_inc;
  always_comb begin
    case (freq_sel)
      2'd0: phase_inc = PH1;
      2'd1: phase_inc = PH2;
      2'd2: phase_inc = PH5;
      2'd3: phase_inc = PH10;
      default: phase_inc = PH1;
    endcase
  end

  //-------------------------------------------------------------------------
  // 4) Phase Accumulator
  //-------------------------------------------------------------------------
  logic [31:0] phase_acc = 32'd0;

  always_ff @(posedge clk) phase_acc <= phase_acc + phase_inc;


  //-------------------------------------------------------------------------
  // 5) Waveform Generators
  //-------------------------------------------------------------------------
  // — Sine via quarter-memory + symmetry
  logic [9:0] data_sine;
  sine_gen sin_i (
    .clk   (clk),
    .phase (phase_acc[31:23]),  // top 9 bits → 0..511
    .out   (data_sine)
  );

  // — Triangle: up/down ramp over full cycle
  logic [9:0] data_tri;
  assign data_tri = phase_acc[31]
                  ? (10'd1023 - phase_acc[30:21]) // descending
                  : phase_acc[30:21];            // ascending

  // — Square: MSB of phase_acc
  logic data_sq;
  assign data_sq = phase_acc[31];

  //-------------------------------------------------------------------------
  // 6) Output Multiplexer
  //-------------------------------------------------------------------------
  always_comb begin
    case (waveform_sel)
      2'b00: dac_out = data_sine;
      2'b01: dac_out = data_tri;
      2'b10: dac_out = {10{data_sq}}; // FULL 10-bit wide square wave
      default: dac_out = data_sine;
    endcase
end

endmodule

miniproject03++/tb_top.sv
`timescale 10ns/10ns

module tb_top;
    // Clock and button signals
    logic        clk;
    logic        boot_n;
    logic        sw_n;

    // 10-bit DAC output bus
    logic [9:0]  dac_out;

    // Instantiate the top-level design
    top uut (
        .clk     (clk),
        .boot_n  (boot_n),
        .sw_n    (sw_n),
        .dac_out (dac_out)
    );

    // Clock generation: 10 ns period (100 MHz)
    initial begin
        clk = 0;
        forever #5 clk = ~clk;
    end

    // Button stimulus
    // Both buttons are active-low (pressed = 0).
    initial begin
        // Initialize unpressed
        boot_n = 1;
        sw_n   = 1;

        // Let the design settle for 200 ns
        #20;

        // Press BOOT (cycle waveform)
        boot_n = 0;  
        #20;        // hold for two clock cycles
        boot_n = 1;
        
        // Wait a bit, then press SW (cycle frequency)
        #500;
        sw_n   = 0;
        #20;
        sw_n   = 1;

        // Press BOOT again
        #500;
        boot_n = 0;
        #20;
        boot_n = 1;

        // Add more presses as desired...
        #2000;

        // Finish simulation
        $finish;
    end

    // Dump waveforms for GTKWave
    initial begin
        $dumpfile("tb_top.vcd");
        $dumpvars(0, tb_top);
        #12000; // Adjust time as needed to capture the waveform
        $finish; // End simulation after 12 ms
    end
endmodule

miniproject03++/tb_top.vcd
$date
	Mon Apr 28 12:22:53 2025
$end
$version
	Icarus Verilog
$end
$timescale
	10ns
$end
$scope module tb_top $end
$var wire 10 ! dac_out [9:0] $end
$var reg 1 " boot_n $end
$var reg 1 # clk $end
$var reg 1 $ sw_n $end
$scope module uut $end
$var wire 1 " boot_n $end
$var wire 1 # clk $end
$var wire 1 $ sw_n $end
$var wire 10 % data_tri [9:0] $end
$var wire 1 & data_sq $end
$var wire 10 ' data_sine [9:0] $end
$var parameter 32 ( PH1 $end
$var parameter 32 ) PH10 $end
$var parameter 32 * PH2 $end
$var parameter 32 + PH5 $end
$var reg 1 , boot_r $end
$var reg 1 - boot_sync0 $end
$var reg 1 . boot_sync1 $end
$var reg 10 / dac_out [9:0] $end
$var reg 2 0 freq_sel [1:0] $end
$var reg 32 1 phase_acc [31:0] $end
$var reg 32 2 phase_inc [31:0] $end
$var reg 1 3 sw_r $end
$var reg 1 4 sw_sync0 $end
$var reg 1 5 sw_sync1 $end
$var reg 2 6 waveform_sel [1:0] $end
$scope module sin_i $end
$var wire 1 # clk $end
$var wire 9 7 phase [8:0] $end
$var wire 9 8 quarter_data [8:0] $end
$var wire 7 9 quarter_address [6:0] $end
$var wire 2 : quadrant [1:0] $end
$var reg 10 ; out [9:0] $end
$scope module mem_inst $end
$var wire 1 # clk $end
$var wire 7 < read_address [6:0] $end
$var parameter 128 = INIT_FILE $end
$var reg 9 > read_data [8:0] $end
$upscope $end
$upscope $end
$upscope $end
$upscope $end
$enddefinitions $end
$comment Show the parameter values. $end
$dumpall
b1110011011010010110111001100101010111110111000101110101011000010111001001110100011001010111001000101110011101000111100001110100 =
b110110100111010000110 +
b10101110110000110011 *
b1101101001100100011011 )
b1010111011000011001 (
$end
#0
$dumpvars
bx >
b0 <
bx ;
b0 :
b0 9
bx 8
b0 7
b0 6
x5
x4
x3
b1010111011000011001 2
b0 1
b0 0
bx /
x.
x-
x,
bx '
0&
b0 %
1$
0#
1"
bx !
$end
#5
b1000000000 !
b1000000000 /
b1000000000 '
b1000000000 ;
b0 8
b0 >
04
0-
b1010111011000011001 1
1#
#10
0#
#15
b10101110110000110010 1
05
0.
1#
#20
0#
0"
#25
1-
03
0,
b100000110001001001011 1
1#
#30
0#
#35
b101011101100001100100 1
1.
1#
#40
0#
1"
#45
0-
1,
b110110100111001111101 1
1#
#50
0#
#55
b1 %
b1 !
b1 /
b1000001100010010010110 1
b1 6
0,
0.
1#
#60
0#
#65
b1001100011101010101111 1
1#
#70
0#
#75
b1010111011000011001000 1
1#
#80
0#
#85
b1100010010011011100001 1
1#
#90
0#
#95
b1101101001110011111010 1
1#
#100
0#
#105
b1111000001001100010011 1
1#
#110
0#
#115
b10 !
b10 /
b10 %
b10000011000100100101100 1
1#
#120
0#
#125
b10001101111111101000101 1
1#
#130
0#
#135
b10011000111010101011110 1
1#
#140
0#
#145
b10100011110101101110111 1
1#
#150
0#
#155
b10101110110000110010000 1
1#
#160
0#
#165
b10111001101011110101001 1
1#
#170
0#
#175
b11 !
b11 /
b11 %
b11000100100110111000010 1
1#
#180
0#
#185
b11001111100001111011011 1
1#
#190
0#
#195
b11011010011100111110100 1
1#
#200
0#
#205
b11100101011000000001101 1
1#
#210
0#
#215
b11110000010011000100110 1
1#
#220
0#
#225
b11111011001110000111111 1
1#
#230
0#
#235
b1 9
b1 <
b100 !
b100 /
b100 %
b1 7
b100000110001001001011000 1
1#
#240
0#
#245
b1000000110 '
b1000000110 ;
b110 8
b110 >
b100010001000100001110001 1
1#
#250
0#
#255
b100011011111111010001010 1
1#
#260
0#
#265
b100100110111010010100011 1
1#
#270
0#
#275
b100110001110101010111100 1
1#
#280
0#
#285
b100111100110000011010101 1
1#
#290
0#
#295
b101 !
b101 /
b101 %
b101000111101011011101110 1
1#
#300
0#
#305
b101010010100110100000111 1
1#
#310
0#
#315
b101011101100001100100000 1
1#
#320
0#
#325
b101101000011100100111001 1
1#
#330
0#
#335
b101110011010111101010010 1
1#
#340
0#
#345
b101111110010010101101011 1
1#
#350
0#
#355
b110 !
b110 /
b110 %
b110001001001101110000100 1
1#
#360
0#
#365
b110010100001000110011101 1
1#
#370
0#
#375
b110011111000011110110110 1
1#
#380
0#
#385
b110101001111110111001111 1
1#
#390
0#
#395
b110110100111001111101000 1
1#
#400
0#
#405
b110111111110101000000001 1
1#
#410
0#
#415
b111 !
b111 /
b111 %
b111001010110000000011010 1
1#
#420
0#
#425
b111010101101011000110011 1
1#
#430
0#
#435
b111100000100110001001100 1
1#
#440
0#
#445
b111101011100001001100101 1
1#
#450
0#
#455
b111110110011100001111110 1
1#
#460
0#
#465
b10 9
b10 <
b1000 !
b1000 /
b1000 %
b10 7
b1000000001010111010010111 1
1#
#470
0#
#475
b1000001101 '
b1000001101 ;
b1000001100010010010110000 1
b1101 8
b1101 >
1#
#480
0#
#485
b1000010111001101011001001 1
1#
#490
0#
#495
b1000100010001000011100010 1
1#
#500
0#
#505
b1000101101000011011111011 1
1#
#510
0#
#515
b1000110111111110100010100 1
1#
#520
0#
#525
b1001 !
b1001 /
b1001 %
b1001000010111001100101101 1
1#
#530
0#
#535
b1001001101110100101000110 1
1#
#540
0#
0$
#545
14
b1001011000101111101011111 1
1#
#550
0#
#555
b1001100011101010101111000 1
15
1#
#560
0#
1$
#565
04
13
b1001101110100101110010001 1
1#
#570
0#
#575
b10101110110000110011 2
b1001111001100000110101010 1
b1 0
03
05
1#
#580
0#
#585
b1010 !
b1010 /
b1010 %
b1010001111010110111011101 1
1#
#590
0#
#595
b1010100101001101000010000 1
1#
#600
0#
#605
b1010111011000011001000011 1
1#
#610
0#
#615
b1011 !
b1011 /
b1011 %
b1011010000111001001110110 1
1#
#620
0#
#625
b1011100110101111010101001 1
1#
#630
0#
#635
b1011111100100101011011100 1
1#
#640
0#
#645
b11 9
b11 <
b1100 !
b1100 /
b1100 %
b11 7
b1100010010011011100001111 1
1#
#650
0#
#655
b1000010011 '
b1000010011 ;
b1100101000010001101000010 1
b10011 8
b10011 >
1#
#660
0#
#665
b1100111110000111101110101 1
1#
#670
0#
#675
b1101 !
b1101 /
b1101 %
b1101010011111101110101000 1
1#
#680
0#
#685
b1101101001110011111011011 1
1#
#690
0#
#695
b1101111111101010000001110 1
1#
#700
0#
#705
b1110 !
b1110 /
b1110 %
b1110010101100000001000001 1
1#
#710
0#
#715
b1110101011010110001110100 1
1#
#720
0#
#725
b1111 !
b1111 /
b1111 %
b1111000001001100010100111 1
1#
#730
0#
#735
b1111010111000010011011010 1
1#
#740
0#
#745
b1111101100111000100001101 1
1#
#750
0#
#755
b100 9
b100 <
b10000 !
b10000 /
b10000 %
b100 7
b10000000010101110101000000 1
1#
#760
0#
#765
b1000011001 '
b1000011001 ;
b11001 8
b11001 >
b10000011000100100101110011 1
1#
#770
0#
#775
b10000101110011010110100110 1
1#
#780
0#
#785
b10001 !
b10001 /
b10001 %
b10001000100010000111011001 1
1#
#790
0#
#795
b10001011010000111000001100 1
1#
#800
0#
#805
b10001101111111101000111111 1
1#
#810
0#
#815
b10010 !
b10010 /
b10010 %
b10010000101110011001110010 1
1#
#820
0#
#825
b10010011011101001010100101 1
1#
#830
0#
#835
b10010110001011111011011000 1
1#
#840
0#
#845
b10011 !
b10011 /
b10011 %
b10011000111010101100001011 1
1#
#850
0#
#855
b10011011101001011100111110 1
1#
#860
0#
#865
b10011110011000001101110001 1
1#
#870
0#
#875
b101 9
b101 <
b10100 !
b10100 /
b10100 %
b101 7
b10100001000110111110100100 1
1#
#880
0#
#885
b1000100000 '
b1000100000 ;
b100000 8
b100000 >
b10100011110101101111010111 1
1#
#890
0#
#895
b10100110100100100000001010 1
1#
#900
0#
#905
b10101 !
b10101 /
b10101 %
b10101001010011010000111101 1
1#
#910
0#
#915
b10101100000010000001110000 1
1#
#920
0#
#925
b10101110110000110010100011 1
1#
#930
0#
#935
b10110 !
b10110 /
b10110 %
b10110001011111100011010110 1
1#
#940
0#
#945
b10110100001110010100001001 1
1#
#950
0#
#955
b10110110111101000100111100 1
1#
#960
0#
#965
b10111 !
b10111 /
b10111 %
b10111001101011110101101111 1
1#
#970
0#
#975
b10111100011010100110100010 1
1#
#980
0#
#985
b10111111001001010111010101 1
1#
#990
0#
#995
b110 9
b110 <
b11000 !
b11000 /
b11000 %
b110 7
b11000001111000001000001000 1
1#
#1000
0#
#1005
b1000100110 '
b1000100110 ;
b100110 8
b100110 >
b11000100100110111000111011 1
1#
#1010
0#
#1015
b11000111010101101001101110 1
1#
#1020
0#
#1025
b11001 !
b11001 /
b11001 %
b11001010000100011010100001 1
1#
#1030
0#
#1035
b11001100110011001011010100 1
1#
#1040
0#
#1045
b11001111100001111100000111 1
1#
#1050
0#
#1055
b11010 !
b11010 /
b11010 %
b11010010010000101100111010 1
1#
#1060
0#
0"
#1065
1-
b11010100111111011101101101 1
1#
#1070
0#
#1075
b11010111101110001110100000 1
1.
1#
#1080
0#
1"
#1085
b11011 !
b11011 /
b11011 %
0-
1,
b11011010011100111111010011 1
1#
#1090
0#
#1095
b0 !
b0 /
b11011101001011110000000110 1
b10 6
0,
0.
1#
#1100
0#
#1105
b11011111111010100000111001 1
1#
#1110
0#
#1115
b111 9
b111 <
b11100 %
b111 7
b11100010101001010001101100 1
1#
#1120
0#
#1125
b1000101100 '
b1000101100 ;
b101100 8
b101100 >
b11100101011000000010011111 1
1#
#1130
0#
#1135
b11101 %
b11101000000110110011010010 1
1#
#1140
0#
#1145
b11101010110101100100000101 1
1#
#1150
0#
#1155
b11101101100100010100111000 1
1#
#1160
0#
#1165
b11110 %
b11110000010011000101101011 1
1#
#1170
0#
#1175
b11110011000001110110011110 1
1#
#1180
0#
#1185
b11110101110000100111010001 1
1#
#1190
0#
#1195
b11111 %
b11111000011111011000000100 1
1#
#1200
0#
#1205
b11111011001110001000110111 1
1#
#1210
0#
#1215
b11111101111100111001101010 1
1#
#1220
0#
#1225
b1000 9
b1000 <
b100000 %
b1000 7
b100000000101011101010011101 1
1#
#1230
0#
#1235
b1000110010 '
b1000110010 ;
b100000011011010011011010000 1
b110010 8
b110010 >
1#
#1240
0#
#1245
b100000110001001001100000011 1
1#
#1250
0#
#1255
b100001 %
b100001000110111111100110110 1
1#
#1260
0#
#1265
b100001011100110101101101001 1
1#
#1270
0#
#1275
b100001110010101011110011100 1
1#
#1280
0#
#1285
b100010 %
b100010001000100001111001111 1
1#
#1290
0#
#1295
b100010011110011000000000010 1
1#
#1300
0#
#1305
b100010110100001110000110101 1
1#
#1310
0#
#1315
b100011 %
b100011001010000100001101000 1
1#
#1320
0#
#1325
b100011011111111010010011011 1
1#
#1330
0#
#1335
b100011110101110000011001110 1
1#
#1340
0#
#1345
b1001 9
b1001 <
b100100 %
b1001 7
b100100001011100110100000001 1
1#
#1350
0#
#1355
b1000111001 '
b1000111001 ;
b100100100001011100100110100 1
b111001 8
b111001 >
1#
#1360
0#
#1365
b100100110111010010101100111 1
1#
#1370
0#
#1375
b100101 %
b100101001101001000110011010 1
1#
#1380
0#
#1385
b100101100010111110111001101 1
1#
#1390
0#
#1395
b100101111000110101000000000 1
1#
#1400
0#
#1405
b100110 %
b100110001110101011000110011 1
1#
#1410
0#
#1415
b100110100100100001001100110 1
1#
#1420
0#
#1425
b100110111010010111010011001 1
1#
#1430
0#
#1435
b100111 %
b100111010000001101011001100 1
1#
#1440
0#
#1445
b100111100110000011011111111 1
1#
#1450
0#
#1455
b100111111011111001100110010 1
1#
#1460
0#
#1465
b1010 9
b1010 <
b101000 %
b1010 7
b101000010001101111101100101 1
1#
#1470
0#
#1475
b1000111111 '
b1000111111 ;
b101000100111100101110011000 1
b111111 8
b111111 >
1#
#1480
0#
#1485
b101000111101011011111001011 1
1#
#1490
0#
#1495
b101001 %
b101001010011010001111111110 1
1#
#1500
0#
#1505
b101001101001001000000110001 1
1#
#1510
0#
#1515
b101001111110111110001100100 1
1#
#1520
0#
#1525
b101010 %
b101010010100110100010010111 1
1#
#1530
0#
#1535
b101010101010101010011001010 1
1#
#1540
0#
#1545
b101011 %
b101011000000100000011111101 1
1#
#1550
0#
#1555
b101011010110010110100110000 1
1#
#1560
0#
#1565
b101011101100001100101100011 1
1#
#1570
0#
#1575
b1011 9
b1011 <
b101100 %
b1011 7
b101100000010000010110010110 1
1#
#1580
0#
#1585
b1001000101 '
b1001000101 ;
b1000101 8
b1000101 >
b101100010111111000111001001 1
1#
#1590
0#
#1595
b101100101101101110111111100 1
1#
#1600
0#
#1605
b101101 %
b101101000011100101000101111 1
1#
#1610
0#
#1615
b101101011001011011001100010 1
1#
#1620
0#
#1625
b101101101111010001010010101 1
1#
#1630
0#
#1635
b101110 %
b101110000101000111011001000 1
1#
#1640
0#
#1645
b101110011010111101011111011 1
1#
#1650
0#
#1655
b101110110000110011100101110 1
1#
#1660
0#
#1665
b101111 %
b101111000110101001101100001 1
1#
#1670
0#
#1675
b101111011100011111110010100 1
1#
#1680
0#
#1685
b101111110010010101111000111 1
1#
#1690
0#
#1695
b1100 9
b1100 <
b110000 %
b1100 7
b110000001000001011111111010 1
1#
#1700
0#
#1705
b1001001100 '
b1001001100 ;
b1001100 8
b1001100 >
b110000011110000010000101101 1
1#
#1710
0#
#1715
b110000110011111000001100000 1
1#
#1720
0#
#1725
b110001 %
b110001001001101110010010011 1
1#
#1730
0#
#1735
b110001011111100100011000110 1
1#
#1740
0#
#1745
b110001110101011010011111001 1
1#
#1750
0#
#1755
b110010 %
b110010001011010000100101100 1
1#
#1760
0#
#1765
b110010100001000110101011111 1
1#
#1770
0#
#1775
b110010110110111100110010010 1
1#
#1780
0#
#1785
b110011 %
b110011001100110010111000101 1
1#
#1790
0#
#1795
b110011100010101000111111000 1
1#
#1800
0#
#1805
b110011111000011111000101011 1
1#
#1810
0#
#1815
b1101 9
b1101 <
b110100 %
b1101 7
b110100001110010101001011110 1
1#
#1820
0#
#1825
b1001010010 '
b1001010010 ;
b1010010 8
b1010010 >
b110100100100001011010010001 1
1#
#1830
0#
#1835
b110100111010000001011000100 1
1#
#1840
0#
#1845
b110101 %
b110101001111110111011110111 1
1#
#1850
0#
#1855
b110101100101101101100101010 1
1#
#1860
0#
#1865
b110101111011100011101011101 1
1#
#1870
0#
#1875
b110110 %
b110110010001011001110010000 1
1#
#1880
0#
#1885
b110110100111001111111000011 1
1#
#1890
0#
#1895
b110110111101000101111110110 1
1#
#1900
0#
#1905
b110111 %
b110111010010111100000101001 1
1#
#1910
0#
#1915
b110111101000110010001011100 1
1#
#1920
0#
#1925
b110111111110101000010001111 1
1#
#1930
0#
#1935
b1110 9
b1110 <
b111000 %
b1110 7
b111000010100011110011000010 1
1#
#1940
0#
#1945
b1001011000 '
b1001011000 ;
b1011000 8
b1011000 >
b111000101010010100011110101 1
1#
#1950
0#
#1955
b111001 %
b111001000000001010100101000 1
1#
#1960
0#
#1965
b111001010110000000101011011 1
1#
#1970
0#
#1975
b111001101011110110110001110 1
1#
#1980
0#
#1985
b111010 %
b111010000001101100111000001 1
1#
#1990
0#
#1995
b111010010111100010111110100 1
1#
#2000
0#
#2005
b111010101101011001000100111 1
1#
#2010
0#
#2015
b111011 %
b111011000011001111001011010 1
1#
#2020
0#
#2025
b111011011001000101010001101 1
1#
#2030
0#
#2035
b111011101110111011011000000 1
1#
#2040
0#
#2045
b1111 9
b1111 <
b111100 %
b1111 7
b111100000100110001011110011 1
1#
#2050
0#
#2055
b1001011110 '
b1001011110 ;
b111100011010100111100100110 1
b1011110 8
b1011110 >
1#
#2060
0#
#2065
b111100110000011101101011001 1
1#
#2070
0#
#2075
b111101 %
b111101000110010011110001100 1
1#
#2080
0#
#2085
b111101011100001001110111111 1
1#
#2090
0#
#2095
b111101110001111111111110010 1
1#
#2100
0#
#2105
b111110 %
b111110000111110110000100101 1
1#
#2110
0#
#2115
b111110011101101100001011000 1
1#
#2120
0#
#2125
b111110110011100010010001011 1
1#
#2130
0#
#2135
b111111 %
b111111001001011000010111110 1
1#
#2140
0#
#2145
b111111011111001110011110001 1
1#
#2150
0#
#2155
b111111110101000100100100100 1
1#
#2160
0#
#2165
b10000 9
b10000 <
b1000000 %
b10000 7
b1000000001010111010101010111 1
1#
#2170
0#
#2175
b1001100100 '
b1001100100 ;
b1000000100000110000110001010 1
b1100100 8
b1100100 >
1#
#2180
0#
#2185
b1000000110110100110110111101 1
1#
#2190
0#
#2195
b1000001 %
b1000001001100011100111110000 1
1#
#2200
0#
#2205
b1000001100010010011000100011 1
1#
#2210
0#
#2215
b1000001111000001001001010110 1
1#
#2220
0#
#2225
b1000010 %
b1000010001101111111010001001 1
1#
#2230
0#
#2235
b1000010100011110101010111100 1
1#
#2240
0#
#2245
b1000010111001101011011101111 1
1#
#2250
0#
#2255
b1000011 %
b1000011001111100001100100010 1
1#
#2260
0#
#2265
b1000011100101010111101010101 1
1#
#2270
0#
#2275
b1000011111011001101110001000 1
1#
#2280
0#
#2285
b10001 9
b10001 <
b1000100 %
b10001 7
b1000100010001000011110111011 1
1#
#2290
0#
#2295
b1001101011 '
b1001101011 ;
b1000100100110111001111101110 1
b1101011 8
b1101011 >
1#
#2300
0#
#2305
b1000100111100110000000100001 1
1#
#2310
0#
#2315
b1000101 %
b1000101010010100110001010100 1
1#
#2320
0#
#2325
b1000101101000011100010000111 1
1#
#2330
0#
#2335
b1000101111110010010010111010 1
1#
#2340
0#
#2345
b1000110 %
b1000110010100001000011101101 1
1#
#2350
0#
#2355
b1000110101001111110100100000 1
1#
#2360
0#
#2365
b1000110111111110100101010011 1
1#
#2370
0#
#2375
b1000111 %
b1000111010101101010110000110 1
1#
#2380
0#
#2385
b1000111101011100000110111001 1
1#
#2390
0#
#2395
b10010 9
b10010 <
b1001000 %
b10010 7
b1001000000001010110111101100 1
1#
#2400
0#
#2405
b1001110001 '
b1001110001 ;
b1110001 8
b1110001 >
b1001000010111001101000011111 1
1#
#2410
0#
#2415
b1001000101101000011001010010 1
1#
#2420
0#
#2425
b1001001 %
b1001001000010111001010000101 1
1#
#2430
0#
#2435
b1001001011000101111010111000 1
1#
#2440
0#
#2445
b1001001101110100101011101011 1
1#
#2450
0#
#2455
b1001010 %
b1001010000100011011100011110 1
1#
#2460
0#
#2465
b1001010011010010001101010001 1
1#
#2470
0#
#2475
b1001010110000000111110000100 1
1#
#2480
0#
#2485
b1001011 %
b1001011000101111101110110111 1
1#
#2490
0#
#2495
b1001011011011110011111101010 1
1#
#2500
0#
#2505
b1001011110001101010000011101 1
1#
#2510
0#
#2515
b10011 9
b10011 <
b1001100 %
b10011 7
b1001100000111100000001010000 1
1#
#2520
0#
#2525
b1001110111 '
b1001110111 ;
b1110111 8
b1110111 >
b1001100011101010110010000011 1
1#
#2530
0#
#2535
b1001100110011001100010110110 1
1#
#2540
0#
#2545
b1001101 %
b1001101001001000010011101001 1
1#
#2550
0#
#2555
b1001101011110111000100011100 1
1#
#2560
0#
#2565
b1001101110100101110101001111 1
1#
#2570
0#
#2575
b1001110 %
b1001110001010100100110000010 1
1#
#2580
0#
#2585
b1001110100000011010110110101 1
1#
#2590
0#
#2595
b1001110110110010000111101000 1
1#
#2600
0#
#2605
b1001111 %
b1001111001100000111000011011 1
1#
#2610
0#
#2615
b1001111100001111101001001110 1
1#
#2620
0#
#2625
b1001111110111110011010000001 1
1#
#2630
0#
#2635
b10100 9
b10100 <
b1010000 %
b10100 7
b1010000001101101001010110100 1
1#
#2640
0#
#2645
b1001111101 '
b1001111101 ;
b1111101 8
b1111101 >
b1010000100011011111011100111 1
1#
#2650
0#
#2655
b1010000111001010101100011010 1
1#
#2660
0#
#2665
b1010001 %
b1010001001111001011101001101 1
1#
#2670
0#
#2675
b1010001100101000001110000000 1
1#
#2680
0#
#2685
b1010001111010110111110110011 1
1#
#2690
0#
#2695
b1010010 %
b1010010010000101101111100110 1
1#
#2700
0#
#2705
b1010010100110100100000011001 1
1#
#2710
0#
#2715
b1010010111100011010001001100 1
1#
#2720
0#
#2725
b1010011 %
b1010011010010010000001111111 1
1#
#2730
0#
#2735
b1010011101000000110010110010 1
1#
#2740
0#
#2745
b1010011111101111100011100101 1
1#
#2750
0#
#2755
b10101 9
b10101 <
b1010100 %
b10101 7
b1010100010011110010100011000 1
1#
#2760
0#
#2765
b1010000011 '
b1010000011 ;
b10000011 8
b10000011 >
b1010100101001101000101001011 1
1#
#2770
0#
#2775
b1010100111111011110101111110 1
1#
#2780
0#
#2785
b1010101 %
b1010101010101010100110110001 1
1#
#2790
0#
#2795
b1010101101011001010111100100 1
1#
#2800
0#
#2805
b1010110 %
b1010110000001000001000010111 1
1#
#2810
0#
#2815
b1010110010110110111001001010 1
1#
#2820
0#
#2825
b1010110101100101101001111101 1
1#
#2830
0#
#2835
b1010111 %
b1010111000010100011010110000 1
1#
#2840
0#
#2845
b1010111011000011001011100011 1
1#
#2850
0#
#2855
b1010111101110001111100010110 1
1#
#2860
0#
#2865
b10110 9
b10110 <
b1011000 %
b10110 7
b1011000000100000101101001001 1
1#
#2870
0#
#2875
b1010001001 '
b1010001001 ;
b1011000011001111011101111100 1
b10001001 8
b10001001 >
1#
#2880
0#
#2885
b1011000101111110001110101111 1
1#
#2890
0#
#2895
b1011001 %
b1011001000101100111111100010 1
1#
#2900
0#
#2905
b1011001011011011110000010101 1
1#
#2910
0#
#2915
b1011001110001010100001001000 1
1#
#2920
0#
#2925
b1011010 %
b1011010000111001010001111011 1
1#
#2930
0#
#2935
b1011010011101000000010101110 1
1#
#2940
0#
#2945
b1011010110010110110011100001 1
1#
#2950
0#
#2955
b1011011 %
b1011011001000101100100010100 1
1#
#2960
0#
#2965
b1011011011110100010101000111 1
1#
#2970
0#
#2975
b1011011110100011000101111010 1
1#
#2980
0#
#2985
b10111 9
b10111 <
b1011100 %
b10111 7
b1011100001010001110110101101 1
1#
#2990
0#
#2995
b1010001111 '
b1010001111 ;
b1011100100000000100111100000 1
b10001111 8
b10001111 >
1#
#3000
0#
#3005
b1011100110101111011000010011 1
1#
#3010
0#
#3015
b1011101 %
b1011101001011110001001000110 1
1#
#3020
0#
#3025
b1011101100001100111001111001 1
1#
#3030
0#
#3035
b1011101110111011101010101100 1
1#
#3040
0#
#3045
b1011110 %
b1011110001101010011011011111 1
1#
#3050
0#
#3055
b1011110100011001001100010010 1
1#
#3060
0#
#3065
b1011110111000111111101000101 1
1#
#3070
0#
#3075
b1011111 %
b1011111001110110101101111000 1
1#
